rlinalg/py.typed
rlinalg/_lstsq.py
rlinalg/_cond.py
rlinalg/_decomp_qr.py
rlinalg/_misc.py
rlinalg/__init__.py
rlinalg/linpack/_linpack.cpython-311-x86_64-linux-gnu.so
rlinalg/linpack/__init__.py
rlinalg/tests/test_qr.py
rlinalg/tests/test_lstsq.py
rlinalg/tests/test_doctest.py
rlinalg/tests/__init__.py
rlinalg-0.1.1.dist-info/WHEEL
rlinalg-0.1.1.dist-info/COPYING
rlinalg-0.1.1.dist-info/RECORD
rlinalg-0.1.1.dist-info/METADATA
rlinalg.libs/libquadmath-776d53b6.so.0.0.0
rlinalg.libs/libgfortran-93980b03.so.5.0.0
rlinalg.libs/libopenblas-r0-11edc3fa.3.15.so
