Metadata-Version: 2.1
Name: rlinalg
Version: 0.1.1
Summary: Linear Algebra routines for Python as implemented in the R language.
Keywords: linalg,linear algebra,qr,linpack,R
Author-Email: Martin Larralde <martin.larralde@embl.de>
License:                     GNU GENERAL PUBLIC LICENSE
Classifier: Development Status :: 3 - Alpha
Classifier: Intended Audience :: Developers
Classifier: Intended Audience :: Science/Research
Classifier: License :: OSI Approved :: GNU General Public License v3 or later (GPLv3+)
Classifier: Operating System :: OS Independent
Classifier: Programming Language :: Fortran
Classifier: Programming Language :: Python :: 3.7
Classifier: Programming Language :: Python :: 3.8
Classifier: Programming Language :: Python :: 3.9
Classifier: Programming Language :: Python :: 3.10
Classifier: Programming Language :: Python :: 3.11
Classifier: Programming Language :: Python :: 3.12
Classifier: Topic :: Scientific/Engineering :: Mathematics
Classifier: Typing :: Typed
Project-URL: Documentation, https://rlinalg.readthedocs.io/en/stable/
Project-URL: Bug tracker, https://github.com/althonos/rlinalg/issues
Project-URL: Changelog, https://github.com/althonos/rlinalg/blob/master/CHANGELOG.md
Project-URL: Coverage, https://codecov.io/gh/althonos/rlinalg/
Project-URL: Builds, https://github.com/althonos/rlinalg/actions
Project-URL: Pypi, https://pypi.org/project/rlinalg
Requires-Python: >=3.7
Requires-Dist: numpy>=1.0
